{"trial_id": "0ba4f07e37b61cd9356ec780d296e3d4", "hyperparameters": {"space": [{"class_name": "Int", "config": {"name": "first_units", "default": null, "conditions": [], "min_value": 1, "max_value": 16, "step": 2, "sampling": null}}, {"class_name": "Int", "config": {"name": "second_units", "default": null, "conditions": [], "min_value": 1, "max_value": 16, "step": 2, "sampling": null}}, {"class_name": "Choice", "config": {"name": "learning_rate", "default": 0.1, "conditions": [], "values": [0.1, 0.05, 0.01, 0.001], "ordered": true}}], "values": {"first_units": 9, "second_units": 7, "learning_rate": 0.1, "tuner/epochs": 15, "tuner/initial_epoch": 0, "tuner/bracket": 0, "tuner/round": 0}}, "metrics": {"metrics": {"loss": {"direction": "min", "observations": [{"value": [0.0014692959375679493], "step": 0}]}, "mean_absolute_error": {"direction": "min", "observations": [{"value": [0.029532896354794502], "step": 0}]}, "mean_absolute_percentage_error": {"direction": "min", "observations": [{"value": [3482907.5], "step": 0}]}, "r_squared": {"direction": "min", "observations": [{"value": [-2.1658605064044045], "step": 0}]}, "val_loss": {"direction": "min", "observations": [{"value": [0.0012997258454561234], "step": 0}]}, "val_mean_absolute_error": {"direction": "min", "observations": [{"value": [0.027804166078567505], "step": 0}]}, "val_mean_absolute_percentage_error": {"direction": "min", "observations": [{"value": [802123.0], "step": 0}]}, "val_r_squared": {"direction": "min", "observations": [{"value": [-1.5302921226261188], "step": 0}]}}}, "score": 0.0012997258454561234, "best_step": 0, "status": "COMPLETED"}