{"trial_id": "bd82d65ce294c634b4af1ccfff5df05c", "hyperparameters": {"space": [{"class_name": "Int", "config": {"name": "units", "default": null, "conditions": [], "min_value": 1, "max_value": 32, "step": 2, "sampling": null}}, {"class_name": "Choice", "config": {"name": "learning_rate", "default": 0.1, "conditions": [], "values": [0.1, 0.05, 0.01, 0.001], "ordered": true}}], "values": {"units": 31, "learning_rate": 0.05, "tuner/epochs": 9, "tuner/initial_epoch": 3, "tuner/bracket": 2, "tuner/round": 1, "tuner/trial_id": "8d047e7ebbc95b2e9d879b0cab1b6ca4"}}, "metrics": {"metrics": {"loss": {"direction": "min", "observations": [{"value": [9.500879059487488e-06], "step": 0}]}, "mean_absolute_error": {"direction": "min", "observations": [{"value": [0.0017881635576486588], "step": 0}]}, "mean_absolute_percentage_error": {"direction": "min", "observations": [{"value": [298194.5], "step": 0}]}, "r_squared": {"direction": "min", "observations": [{"value": [-56.76203056712034], "step": 0}]}, "val_loss": {"direction": "min", "observations": [{"value": [1.053565301845083e-05], "step": 0}]}, "val_mean_absolute_error": {"direction": "min", "observations": [{"value": [0.002056820085272193], "step": 0}]}, "val_mean_absolute_percentage_error": {"direction": "min", "observations": [{"value": [252995.71875], "step": 0}]}, "val_r_squared": {"direction": "min", "observations": [{"value": [0.7608244905196406], "step": 0}]}}}, "score": 1.053565301845083e-05, "best_step": 0, "status": "COMPLETED"}