{"trial_id": "12e68ec30df9a93620fa395e17820817", "hyperparameters": {"space": [{"class_name": "Choice", "config": {"name": "units", "default": 4, "conditions": [], "values": [4, 12, 16, 24, 32, 48, 64], "ordered": true}}, {"class_name": "Choice", "config": {"name": "learning_rate", "default": 0.1, "conditions": [], "values": [0.1, 0.01, 0.001, 0.0001], "ordered": true}}], "values": {"units": 12, "learning_rate": 0.1, "tuner/epochs": 25, "tuner/initial_epoch": 0, "tuner/bracket": 0, "tuner/round": 0}}, "metrics": {"metrics": {"loss": {"direction": "min", "observations": [{"value": [4.3710338104574475e-06], "step": 0}]}, "mean_absolute_error": {"direction": "min", "observations": [{"value": [0.001377635169774294], "step": 0}]}, "mean_absolute_percentage_error": {"direction": "min", "observations": [{"value": [346672.6875], "step": 0}]}, "r_squared": {"direction": "min", "observations": [{"value": [-7453.51983585791], "step": 0}]}, "val_loss": {"direction": "min", "observations": [{"value": [4.506357072386891e-06], "step": 0}]}, "val_mean_absolute_error": {"direction": "min", "observations": [{"value": [0.00113653764128685], "step": 0}]}, "val_mean_absolute_percentage_error": {"direction": "min", "observations": [{"value": [160420.96875], "step": 0}]}, "val_r_squared": {"direction": "min", "observations": [{"value": [-1137.0293842925435], "step": 0}]}}}, "score": 4.506357072386891e-06, "best_step": 0, "status": "COMPLETED"}