{"trial_id": "b5ff17a172456ab3cad3b0fb13d4d98d", "hyperparameters": {"space": [{"class_name": "Int", "config": {"name": "first_units", "default": null, "conditions": [], "min_value": 1, "max_value": 16, "step": 2, "sampling": null}}, {"class_name": "Int", "config": {"name": "second_units", "default": null, "conditions": [], "min_value": 1, "max_value": 16, "step": 2, "sampling": null}}, {"class_name": "Choice", "config": {"name": "learning_rate", "default": 0.1, "conditions": [], "values": [0.1, 0.05, 0.01, 0.001], "ordered": true}}], "values": {"first_units": 7, "second_units": 15, "learning_rate": 0.05, "tuner/epochs": 9, "tuner/initial_epoch": 3, "tuner/bracket": 2, "tuner/round": 1, "tuner/trial_id": "1e1842c38ca291864530b55aa7181a69"}}, "metrics": {"metrics": {"loss": {"direction": "min", "observations": [{"value": [0.0008463942212983966], "step": 0}]}, "mean_absolute_error": {"direction": "min", "observations": [{"value": [0.02131863497197628], "step": 0}]}, "mean_absolute_percentage_error": {"direction": "min", "observations": [{"value": [26.82958984375], "step": 0}]}, "r_squared": {"direction": "min", "observations": [{"value": [-5.488158180513325], "step": 0}]}, "val_loss": {"direction": "min", "observations": [{"value": [0.0008020822424441576], "step": 0}]}, "val_mean_absolute_error": {"direction": "min", "observations": [{"value": [0.022050928324460983], "step": 0}]}, "val_mean_absolute_percentage_error": {"direction": "min", "observations": [{"value": [25.450300216674805], "step": 0}]}, "val_r_squared": {"direction": "min", "observations": [{"value": [-0.05996596749086591], "step": 0}]}}}, "score": 0.0008020822424441576, "best_step": 0, "status": "COMPLETED"}