{"trial_id": "b7d0675ed1036aa96ce4201404d94003", "hyperparameters": {"space": [{"class_name": "Choice", "config": {"name": "units", "default": 4, "conditions": [], "values": [4, 12, 16, 24, 32, 48, 64], "ordered": true}}, {"class_name": "Choice", "config": {"name": "learning_rate", "default": 0.1, "conditions": [], "values": [0.1, 0.01, 0.001, 0.0001], "ordered": true}}], "values": {"units": 24, "learning_rate": 0.0001, "tuner/epochs": 9, "tuner/initial_epoch": 3, "tuner/bracket": 2, "tuner/round": 1, "tuner/trial_id": "84c5d18514767845c18aab2f71b90d9e"}}, "metrics": {"metrics": {"loss": {"direction": "min", "observations": [{"value": [0.011336593888700008], "step": 0}]}, "mean_absolute_error": {"direction": "min", "observations": [{"value": [0.10588382184505463], "step": 0}]}, "mean_absolute_percentage_error": {"direction": "min", "observations": [{"value": [4942.1318359375], "step": 0}]}, "r_squared": {"direction": "min", "observations": [{"value": [-79.81780145856274], "step": 0}]}, "val_loss": {"direction": "min", "observations": [{"value": [0.011266243644058704], "step": 0}]}, "val_mean_absolute_error": {"direction": "min", "observations": [{"value": [0.10548873245716095], "step": 0}]}, "val_mean_absolute_percentage_error": {"direction": "min", "observations": [{"value": [2730.6201171875], "step": 0}]}, "val_r_squared": {"direction": "min", "observations": [{"value": [-69.77477468616428], "step": 0}]}}}, "score": 0.011266243644058704, "best_step": 0, "status": "COMPLETED"}