{"trial_id": "da467a18d178f81b6d82808d16210647", "hyperparameters": {"space": [{"class_name": "Int", "config": {"name": "first_units", "default": null, "conditions": [], "min_value": 2, "max_value": 32, "step": 2, "sampling": null}}, {"class_name": "Int", "config": {"name": "second_units", "default": null, "conditions": [], "min_value": 2, "max_value": 32, "step": 2, "sampling": null}}, {"class_name": "Choice", "config": {"name": "learning_rate", "default": 0.1, "conditions": [], "values": [0.1, 0.05, 0.01, 0.001, 0.0001], "ordered": true}}], "values": {"first_units": 6, "second_units": 10, "learning_rate": 0.05, "tuner/epochs": 9, "tuner/initial_epoch": 0, "tuner/bracket": 1, "tuner/round": 0}}, "metrics": {"metrics": {"loss": {"direction": "min", "observations": [{"value": [0.00041656673420220613], "step": 0}]}, "mean_absolute_error": {"direction": "min", "observations": [{"value": [0.014018255285918713], "step": 0}]}, "mean_absolute_percentage_error": {"direction": "min", "observations": [{"value": [16.636722564697266], "step": 0}]}, "r_squared": {"direction": "min", "observations": [{"value": [-3.107257202675413], "step": 0}]}, "val_loss": {"direction": "min", "observations": [{"value": [0.0003062713367398828], "step": 0}]}, "val_mean_absolute_error": {"direction": "min", "observations": [{"value": [0.012463155202567577], "step": 0}]}, "val_mean_absolute_percentage_error": {"direction": "min", "observations": [{"value": [14.643675804138184], "step": 0}]}, "val_r_squared": {"direction": "min", "observations": [{"value": [0.19624759821179039], "step": 0}]}}}, "score": 0.0003062713367398828, "best_step": 0, "status": "COMPLETED"}