{"trial_id": "c2be361dcb08ffa96c741dea7672469f", "hyperparameters": {"space": [{"class_name": "Int", "config": {"name": "first_units", "default": null, "conditions": [], "min_value": 1, "max_value": 16, "step": 2, "sampling": null}}, {"class_name": "Int", "config": {"name": "second_units", "default": null, "conditions": [], "min_value": 1, "max_value": 16, "step": 2, "sampling": null}}, {"class_name": "Choice", "config": {"name": "learning_rate", "default": 0.1, "conditions": [], "values": [0.1, 0.05, 0.01, 0.001], "ordered": true}}], "values": {"first_units": 5, "second_units": 1, "learning_rate": 0.1, "tuner/epochs": 15, "tuner/initial_epoch": 0, "tuner/bracket": 0, "tuner/round": 0}}, "metrics": {"metrics": {"loss": {"direction": "min", "observations": [{"value": [0.004193857777863741], "step": 0}]}, "mean_absolute_error": {"direction": "min", "observations": [{"value": [0.05450870841741562], "step": 0}]}, "mean_absolute_percentage_error": {"direction": "min", "observations": [{"value": [124631.109375], "step": 0}]}, "r_squared": {"direction": "min", "observations": [{"value": [-0.10814243629334386], "step": 0}]}, "val_loss": {"direction": "min", "observations": [{"value": [0.0037185123655945063], "step": 0}]}, "val_mean_absolute_error": {"direction": "min", "observations": [{"value": [0.05098621919751167], "step": 0}]}, "val_mean_absolute_percentage_error": {"direction": "min", "observations": [{"value": [60584.86328125], "step": 0}]}, "val_r_squared": {"direction": "min", "observations": [{"value": [-0.21656315063918297], "step": 0}]}}}, "score": 0.0037185123655945063, "best_step": 0, "status": "COMPLETED"}