{"trial_id": "c085138825940432c31982f9d783064a", "hyperparameters": {"space": [{"class_name": "Int", "config": {"name": "first_units", "default": null, "conditions": [], "min_value": 2, "max_value": 32, "step": 2, "sampling": null}}, {"class_name": "Int", "config": {"name": "second_units", "default": null, "conditions": [], "min_value": 2, "max_value": 32, "step": 2, "sampling": null}}, {"class_name": "Choice", "config": {"name": "learning_rate", "default": 0.1, "conditions": [], "values": [0.1, 0.05, 0.01, 0.001, 0.0001], "ordered": true}}], "values": {"first_units": 28, "second_units": 10, "learning_rate": 0.001, "tuner/epochs": 25, "tuner/initial_epoch": 9, "tuner/bracket": 2, "tuner/round": 2, "tuner/trial_id": "328ebc914ea61d0ecf3dbe30b17184a2"}}, "metrics": {"metrics": {"loss": {"direction": "min", "observations": [{"value": [0.0001823554193833843], "step": 0}]}, "mean_absolute_error": {"direction": "min", "observations": [{"value": [0.010006111115217209], "step": 0}]}, "mean_absolute_percentage_error": {"direction": "min", "observations": [{"value": [5658.3056640625], "step": 0}]}, "r_squared": {"direction": "min", "observations": [{"value": [0.024499479120675516], "step": 0}]}, "val_loss": {"direction": "min", "observations": [{"value": [0.0001510996517026797], "step": 0}]}, "val_mean_absolute_error": {"direction": "min", "observations": [{"value": [0.00941208191215992], "step": 0}]}, "val_mean_absolute_percentage_error": {"direction": "min", "observations": [{"value": [11850.6640625], "step": 0}]}, "val_r_squared": {"direction": "min", "observations": [{"value": [0.06488622841730596], "step": 0}]}}}, "score": 0.0001510996517026797, "best_step": 0, "status": "COMPLETED"}