{"trial_id": "1569f5913ee3a4dc3a90d8daf82af5c6", "hyperparameters": {"space": [{"class_name": "Choice", "config": {"name": "first_units", "default": 4, "conditions": [], "values": [4, 12, 16, 24, 32], "ordered": true}}, {"class_name": "Choice", "config": {"name": "second_units", "default": 4, "conditions": [], "values": [4, 12, 16, 24, 32], "ordered": true}}, {"class_name": "Choice", "config": {"name": "learning_rate", "default": 0.1, "conditions": [], "values": [0.1, 0.01, 0.001, 0.0001], "ordered": true}}], "values": {"first_units": 16, "second_units": 32, "learning_rate": 0.01, "tuner/epochs": 25, "tuner/initial_epoch": 9, "tuner/bracket": 1, "tuner/round": 1, "tuner/trial_id": "6a7a17ae163e4f927b420fc1da00cc03"}}, "metrics": {"metrics": {"loss": {"direction": "min", "observations": [{"value": [2.0065974695171462e-06], "step": 0}]}, "mean_absolute_error": {"direction": "min", "observations": [{"value": [0.0010526154655963182], "step": 0}]}, "mean_absolute_percentage_error": {"direction": "min", "observations": [{"value": [50450.8671875], "step": 0}]}, "r_squared": {"direction": "min", "observations": [{"value": [0.5323599223169977], "step": 0}]}, "val_loss": {"direction": "min", "observations": [{"value": [5.932460567237285e-07], "step": 0}]}, "val_mean_absolute_error": {"direction": "min", "observations": [{"value": [0.0005715636652894318], "step": 0}]}, "val_mean_absolute_percentage_error": {"direction": "min", "observations": [{"value": [30465.005859375], "step": 0}]}, "val_r_squared": {"direction": "min", "observations": [{"value": [0.8545472149710199], "step": 0}]}}}, "score": 5.932460567237285e-07, "best_step": 0, "status": "COMPLETED"}