{"trial_id": "b4dc0b2b4c7c1a5216555dc09d5745ff", "hyperparameters": {"space": [{"class_name": "Int", "config": {"name": "first_units", "default": null, "conditions": [], "min_value": 1, "max_value": 16, "step": 2, "sampling": null}}, {"class_name": "Int", "config": {"name": "second_units", "default": null, "conditions": [], "min_value": 1, "max_value": 16, "step": 2, "sampling": null}}, {"class_name": "Choice", "config": {"name": "learning_rate", "default": 0.1, "conditions": [], "values": [0.1, 0.05, 0.01, 0.001], "ordered": true}}], "values": {"first_units": 9, "second_units": 15, "learning_rate": 0.001, "tuner/epochs": 9, "tuner/initial_epoch": 3, "tuner/bracket": 2, "tuner/round": 1, "tuner/trial_id": "de8b9a9e6d23e059f2ae49c206c7290c"}}, "metrics": {"metrics": {"loss": {"direction": "min", "observations": [{"value": [6.655624929408077e-06], "step": 0}]}, "mean_absolute_error": {"direction": "min", "observations": [{"value": [0.0017519054235890508], "step": 0}]}, "mean_absolute_percentage_error": {"direction": "min", "observations": [{"value": [452461.03125], "step": 0}]}, "r_squared": {"direction": "min", "observations": [{"value": [-19.657709381811998], "step": 0}]}, "val_loss": {"direction": "min", "observations": [{"value": [7.236545116029447e-06], "step": 0}]}, "val_mean_absolute_error": {"direction": "min", "observations": [{"value": [0.0017552328063175082], "step": 0}]}, "val_mean_absolute_percentage_error": {"direction": "min", "observations": [{"value": [429072.09375], "step": 0}]}, "val_r_squared": {"direction": "min", "observations": [{"value": [0.842056883175782], "step": 0}]}}}, "score": 7.236545116029447e-06, "best_step": 0, "status": "COMPLETED"}