{"trial_id": "452f2d14b62972e41300be4c7a590efc", "hyperparameters": {"space": [{"class_name": "Choice", "config": {"name": "units", "default": 4, "conditions": [], "values": [4, 12, 16, 24, 32, 48, 64], "ordered": true}}, {"class_name": "Choice", "config": {"name": "learning_rate", "default": 0.1, "conditions": [], "values": [0.1, 0.01, 0.001, 0.0001], "ordered": true}}], "values": {"units": 24, "learning_rate": 0.01, "tuner/epochs": 9, "tuner/initial_epoch": 0, "tuner/bracket": 1, "tuner/round": 0}}, "metrics": {"metrics": {"loss": {"direction": "min", "observations": [{"value": [1.972063364519272e-05], "step": 0}]}, "mean_absolute_error": {"direction": "min", "observations": [{"value": [0.003403811017051339], "step": 0}]}, "mean_absolute_percentage_error": {"direction": "min", "observations": [{"value": [31.702392578125], "step": 0}]}, "r_squared": {"direction": "min", "observations": [{"value": [-10.81552226206895], "step": 0}]}, "val_loss": {"direction": "min", "observations": [{"value": [1.4517017916659825e-05], "step": 0}]}, "val_mean_absolute_error": {"direction": "min", "observations": [{"value": [0.003065139753744006], "step": 0}]}, "val_mean_absolute_percentage_error": {"direction": "min", "observations": [{"value": [20.093944549560547], "step": 0}]}, "val_r_squared": {"direction": "min", "observations": [{"value": [0.4562131090105259], "step": 0}]}}}, "score": 1.4517017916659825e-05, "best_step": 0, "status": "COMPLETED"}